LICENSE.txt
README.md
pyproject.toml
setup.cfg
setup.py
src/libdrm/__init__.py
src/libdrm/common.py
src/libdrm/datamodels.py
src/libdrm/elastic.py
src/libdrm/pipelines.py
src/libdrm.egg-info/PKG-INFO
src/libdrm.egg-info/SOURCES.txt
src/libdrm.egg-info/dependency_links.txt
src/libdrm.egg-info/requires.txt
src/libdrm.egg-info/top_level.txt