Metadata-Version: 2.1
Name: libdrm
Version: 0.1.10
Summary: Common helper modules shared by the pipeline services
Home-page: https://github.com/panc86/smdrm
Author: Emanuele Panizio
Author-email: emanuele.panizio@ext.ec.europa.eu
License: UNKNOWN
Project-URL: Bug Reports, https://github.com/panc86/smdrm/issues
Project-URL: Kanban, https://github.com/panc86/smdrm/projects/1
Project-URL: Source, https://github.com/panc86/smdrm
Platform: UNKNOWN
Classifier: Development Status :: 3 - Alpha
Classifier: Intended Audience :: Developers
Classifier: Topic :: Software Development :: Build Tools
Classifier: License :: OSI Approved :: European Union Public Licence 1.2 (EUPL 1.2)
Classifier: Programming Language :: Python :: 3
Classifier: Programming Language :: Python :: 3.7
Classifier: Programming Language :: Python :: 3.8
Classifier: Programming Language :: Python :: 3 :: Only
Requires-Python: >3.7, <3.10
License-File: LICENSE.txt
